{"prefecture":"千葉県","cities":{"千葉市中央区":["旭町","亥鼻","稲荷町","院内","鵜の森町","栄町","塩田町","花輪町","葛城","寒川町","亀井町","亀岡町","宮崎","宮崎町","港町","今井","今井町","市場町","汐見丘町","若草","出洲港","春日","松ケ丘町","松波","新宿","新千葉","新町","新田町","新浜町","神明町","仁戸名町","星久喜町","生実町","青葉町","赤井町","千葉港","千葉寺町","川戸町","川崎町","蘇我","蘇我町","村田町","大巌寺町","大森町","中央","中央港","長洲","椿森","鶴沢町","登戸","都町","東千葉","東本町","道場南","道場北","南生実町","南町","白旗","浜野町","富士見","弁天","本千葉町","本町","末広","問屋町","矢作町","祐光","要町"],"千葉市花見川区":["こてはし台","さつきが丘","み春野","宇那谷町","横戸台","横戸町","花園","花園町","花見川","花島町","宮野木台","検見川町","作新台","三角町","瑞穂","西小中台","千種町","大日町","朝日ケ丘","朝日ケ丘町","長作台","長作町","天戸町","内山町","南花園","柏井","柏井町","畑町","武石町","幕張町","幕張本郷","浪花町","犢橋町"],"千葉市稲毛区":["あやめ台","稲丘町","稲毛","稲毛台町","稲毛町","稲毛東","園生町","宮野木町","穴川","穴川町","轟町","黒砂","黒砂台","作草部","作草部町","山王町","小深町","小中台町","小仲台","千草台","長沼原町","長沼町","天台","天台町","萩台町","柏台","弥生町","緑町","六方町"],"千葉市若葉区":["みつわ台","愛生町","下泉町","下田町","加曽利町","貝塚","貝塚町","金親町","原町","源町","古泉町","五十土町","御成台","御殿町","更科町","高根町","高品町","佐和町","坂月町","桜木","桜木北","若松台","若松町","小間子町","小倉台","小倉町","上泉町","西都賀","千城台西","千城台東","千城台南","千城台北","川井町","多部田町","太田町","大井戸町","大宮台","大宮町","大広町","大草町","谷当町","旦谷町","中田町","中野町","殿台町","都賀","都賀の台","東寺山町","富田町","北大宮台","北谷津町","野呂町","和泉町"],"千葉市緑区":["あすみが丘","あすみが丘東","おゆみ野","おゆみ野中央","おゆみ野南","おゆみ野有吉","越智町","下大和田町","鎌取町","刈田子町","古市場町","高津戸町","高田町","小金沢町","小山町","小食土町","上大和田町","大金沢町","大高町","大膳野町","大椎町","大木戸町","大野台","中西町","椎名崎町","土気町","東山科町","板倉町","富岡町","平山町","平川町","辺田町","茂呂町","誉田町","落井町"],"千葉市美浜区":["ひび野","磯辺","稲毛海岸","幸町","高洲","高浜","若葉","新港","真砂","打瀬","中瀬","中瀬ワールドビジネスガーデン","美浜","浜田","豊砂","幕張西"],"銚子市":["愛宕町","芦崎町","粟島町","栄町","猿田町","岡野台町","海鹿島町","外川台町","外川町","垣根見晴台","垣根町","笠上町","宮原町","橋本町","君ケ浜","犬若","犬吠埼","後飯町","幸町","港町","高神原町","高神西町","高神東町","高田町","高野町","黒生町","今宮町","榊町","桜井町","笹本町","三軒町","三崎町","三宅町","三門町","四日市場台","四日市場町","柴崎町","若宮町","春日台町","春日町","諸持町","小船木町","小長町","小畑新町","小畑町","小浜町","松岸見晴台","松岸町","松本町","上野町","常世田町","植松町","新生町","新地町","新町","森戸町","親田町","陣屋町","正明寺町","清水町","清川町","西芝町","西小川町","赤塚町","川口町","船木町","前宿町","双葉町","台町","大橋町","竹町","茶畑町","中央町","中島町","仲町","潮見町","長崎町","長山町","長塚町","通町","塚本町","天王台","田中町","唐子町","東芝町","東小川町","東町","内浜町","南小川町","南町","忍町","馬場町","白石町","八幡町","八木町","飯沼町","浜町","富川町","豊里台","北小川町","本城町","本町","末広町","妙見町","名洗町","明神町","野尻町","弥生町","余山町","和田町"],"市川市":["伊勢宿","稲越","稲荷木","塩焼","塩浜","押切","下貝塚","下新宿","下妙典","加藤新田","河原","関ケ島","鬼越","鬼高","宮久保","欠真間","原木","幸","広尾","行徳駅前","香取","高石神","高谷","高谷新町","高浜町","国府台","国分","市川","市川南","若宮","上妙典","新井","新田","新浜","真間","須和田","菅野","千鳥町","曽谷","相之川","大洲","大町","大野町","大和田","中国分","中山","田尻","島尻","東国分","東菅野","東大和田","東浜","南行徳","南大野","南八幡","二俣","二俣新町","日之出","入船","柏井町","八幡","富浜","福栄","平田","奉免町","宝","北国分","北方","北方町","堀之内","本塩","本行徳","本北方","末広","湊","湊新田","妙典"],"船橋市":["みやぎ台","旭町","印内","印内町","栄町","夏見","夏見台","夏見町","海神","海神町","海神町西","海神町東","海神町南","葛飾町","丸山","宮本","金杉","金杉台","金杉町","金堀町","古作","古作町","古和釜町","行田","行田町","高根台","高根町","高瀬町","高野台","咲が丘","三咲","三咲町","三山","山手","山野町","市場","七林町","芝山","車方町","若松","習志野","習志野台","駿河台","小室町","小野田町","松が丘","上山町","新高根","神保町","西浦","西習志野","西船","前貝塚町","前原西","前原東","大穴町","大穴南","大穴北","大神保町","滝台","滝台町","中野木","潮見町","坪井西","坪井町","坪井東","田喜野井","東船橋","東中山","東町","藤原","南海神","南三咲","南本町","楠が山町","二宮","二子町","二和西","二和東","日の出","馬込西","馬込町","八木が谷","八木が谷町","飯山満町","浜町","米ケ崎町","豊富町","北本町","本郷町","本中山","本町","湊町","薬円台","薬園台町","緑台","鈴身町"],"館山市":["安東","安布里","伊戸","稲","薗","塩見","岡田","下真倉","加賀名","笠名","館山","亀ケ原","宮城","犬石","見物","古茂口","広瀬","江田","香","高井","国分","腰越","佐野","坂井","坂足","坂田","作名","山荻","山本","洲宮","洲崎","出野尾","小原","小沼","沼","上真倉","上野原","新宿","神余","水岡","水玉","正木","西川名","西長田","川名","船形","早物","相浜","大井","大賀","大戸","大神宮","大網","竹原","中里","長須賀","東長田","藤原","那古","南条","二子","波左間","畑","八幡","飯沼","浜田","富士見","布沼","布良","宝貝","北条","北条正木","湊","茂名","竜岡"],"木更津市":["かずさ鎌足","ほたる野","伊豆島","井尻","羽鳥野","瓜倉","永井作","下烏田","下宮田","下郡","下内橋","下望陀","貝渕","茅野","茅野七曲","岩根","祇園","久津間","牛込","牛袋","牛袋野","金田東","犬成","戸国","吾妻","幸町","江川","港南台","高砂","高柳","根岸","佐野","坂戸市場","桜井","桜井新町","桜町","笹子","山本七曲","若葉町","十日市場","小浜","上烏田","上根岸","上望陀","新港","新宿","新田","真舟","真里","真里谷","菅生","清見台","清見台東","清見台南","清川","西岩根","請西","請西東","請西南","千束台","曽根","草敷","太田","大稲","大久保","大寺","大和","築地","中の島","中烏田","中央","中島","中島地先海ほたる","中尾","中野","中里","朝日","潮見","潮浜","長須賀","椿","田川","東太田","東中央","日の出町","畑沢","畑沢南","八幡台","畔戸","富士見","文京","北浜町","本郷","万石","木更津","木材港","矢那","有吉"],"松戸市":["旭町","栄町","栄町西","横須賀","下矢切","河原塚","岩瀬","吉井町","久保平賀","金ケ作","串崎新田","串崎南町","栗ケ沢","栗山","古ケ崎","胡録台","五香","五香西","五香南","五香六実","幸谷","幸田","高塚新田","高柳","高柳新田","根本","根木内","三ケ月","三矢小台","紙敷","七右衛門新田","主水新田","秋山","初富飛地","小金","小金きよしケ丘","小金原","小金上総町","小金清志町","小根本","小山","松戸","松戸新田","松飛台","上総内","上本郷","上矢切","常盤平","常盤平松葉町","常盤平陣屋前","常盤平西窪町","常盤平双葉町","常盤平柳町","新作","新松戸","新松戸東","新松戸南","新松戸北","西馬橋","西馬橋幸町","西馬橋広手町","西馬橋相川町","西馬橋蔵元町","千駄堀","大橋","大金平","大谷口","大谷口新田","竹ケ花","竹ケ花西町","中金杉","中根","中根長津町","中矢切","中和倉","仲井町","殿平賀","田中新田","東松戸","東平賀","南花島","二ツ木","二ツ木二葉町","二十世紀が丘柿の木町","二十世紀が丘丸山町","二十世紀が丘戸山町","二十世紀が丘中松町","二十世紀が丘萩町","二十世紀が丘美野里町","二十世紀が丘梨元町","日暮","馬橋","八ケ崎","八ケ崎緑町","樋野口","平賀","北松戸","牧の原","本町","稔台","野菊野","緑ケ丘","六高台","六高台西","六実","和名ケ谷"],"野田市":["つつみ野","なみき","はやま","みずき","横内","岡田","下三ケ尾","花井","関宿元町","関宿江戸町","関宿三軒家","関宿台町","関宿町","関宿内町","丸井","岩名","吉春","宮崎","桐ケ作","金杉","古布内","五木","五木新町","五木新田","光葉町","今上","座生","桜の里","桜台","桜木","三ツ堀","山崎","山崎貝塚町","山崎新町","山崎梅の台","次木","七光台","春日町","小山","上花輪","上花輪新町","上三ケ尾","新田戸","親野井","瀬戸","清水","清水公園東","西高野","西三ケ尾","泉","船形","大殿井","谷津","中戸","中根","中野台","中野台鹿島町","中里","鶴奉","堤根","堤台","東金野井","東高野","東宝珠花","二ツ塚","日の出町","梅郷","柏寺","蕃昌","尾崎","尾崎台","平井","木間ケ瀬","木野崎","目吹","野田","柳沢","莚打"],"茂原市":["にいはる工業団地","ゆたか","芦網","粟生野","榎神房","榎神房飛地","猿袋","押日","下永吉","下太田","萱場","吉井下","吉井上","弓渡","桂","桂飛地","御蔵芝","綱島","高師","高師台","高師町","高田","国府関","黒戸","腰当","三ケ谷","山崎","七渡","柴名","渋谷","小萱場","小轡","小林","庄吉","上永吉","上太田","上茂原","上林","新小轡","真名","清水","西野","石神","千代田町","千沢","千町","川島飛地","早野","早野新田","台田","大芝","大沢","大登","谷本","中の島町","中善寺","中之郷飛地","中部","町保","長清水","長谷","長尾","東郷","東部台","東茂原","道表","内長谷","南吉田","萩原町","八千代","八幡原","法目","北高根飛地","北塚","墨田","本小轡","本納","箕輪","茂原","茂原西","木崎","野牛","立木","緑ケ丘","緑町","六ツ野","六田台","鷲巣"],"成田市":["ウイング土屋","はなのき台","芦田","安西","伊能","囲護台","磯部","一坪田","稲荷山","臼作","猿山","押畑","横山","下金山","下福田","下方","加良部","花崎町","滑川","官林","関戸","吉岡","吉倉","久井崎","久住中央","久米","久米野","橋賀台","郷部","玉造","駒井野","古込","吾妻","御所の内","公津の杜","幸町","江弁須","荒海","高","高岡","高倉","佐野","桜田","三里塚","三里塚御料","三里塚光ケ丘","山口","山之作","四谷","寺台","七沢","柴田","芝","取香","宗吾","十余三","所","小菅","小泉","小浮","小野","松崎","松子","上町","上福田","新駒井野","新妻","新川","新泉","新町","新田","水の上","水掛","成井","成田","成毛","西三里塚","西大須賀","西和泉","青山","赤荻","赤坂","川栗","川上","浅間","船形","前林","倉水","村田","多良貝","台方","大栄十余三","大山","大室","大沼","大菅","大清水","大生","大袋","大竹","大和田","地蔵原新田","中台","中野","中里","仲町","長沼","長田","津富浦","天神峰","天浪","田町","土屋","土室","冬父","東ノ台","東金山","東三里塚","東町","東峰","東和泉","東和田","奈土","南羽鳥","南三里塚","南敷","南部","南平台","馬橋","馬乗里","馬場","幡谷","畑ケ田","八代","飯岡","飯仲","飯田町","美郷台","不動ケ岡","並木町","米野","宝田","北羽鳥","北須賀","北部","堀之内","堀籠","本三里塚","本城","本町","名古屋","名木","木の根","野馬込","野毛平","竜台","和田"],"佐倉市":["ユーカリが丘","井野","井野町","稲荷台","印南","羽鳥","臼井","臼井台","臼井田","瓜坪新田","栄町","王子台","下根","下根町","下志津","下志津原","下勝田","海隣寺町","角来","寒風","岩富","岩富町","岩名","吉見","宮ノ台","宮小路町","宮前","宮内","宮本","江原","江原新田","江原台","高岡","高崎","最上町","坂戸","山王","山崎","寺崎","寺崎北","鹿島干拓","七曲","樹木町","春路","将門町","小篠塚","小竹","上座","上志津","上志津原","上勝田","上代","上別所","城","城内町","新臼井田","新町","神門","生谷","西ユーカリが丘","西御門","西志津","青菅","石川","先崎","千成","染井野","太田","大佐倉","大崎台","大作","大篠塚","大蛇町","中志津","中尾余町","長熊","直弥","坪山新田","鏑木仲田町","鏑木町","天辺","田町","土浮","藤治台","藤沢町","内田","鍋山町","南ユーカリが丘","南臼井台","馬渡","萩山新田","白銀","八幡台","八木","畔田","飯重","飯塚","飯田","飯田台","飯野","飯野町","表町","並木町","米戸","本町","木野子","野狐台町","弥勒町","裏新町","六崎"],"東金市":["粟生飛地","依古島","一之袋","押堀","下谷","下武射田","家徳","家之子","関下","関内","季美の森東","丘山台","宮","求名","極楽寺","御門","幸田","広瀬","荒生","高倉","砂古瀬","細屋敷","三ケ尻","三浦名","山口","山田","士農田","酒蔵","宿","小沼田","小野","松之郷","上谷","上布田","上武射田","西中","西福俵","西野飛地","川場","前之内","台方","大沼","大沼田","大豆谷","滝","滝沢","丹尾","中野","殿廻","田間","田中","東岩崎","東金","東上宿","東新宿","東中","東中島","藤下飛地","道庭","南上宿","二之袋","二又","日吉台","薄島","八坂台","菱沼","不動堂飛地","福俵","北幸谷","北之幸谷","堀上","堀之内","油井"],"旭市":["１７２８－４番地","３５９８～３６１４番地","イ","さくら台","ニ","ハ","ロ","井戸野","横根","下永井","鎌数","関戸","岩井","岩崎","幾世","琴田","琴田８５～１６０、１３８６～１８１５、２５９３～２８２０、","駒込","権田沼新田","見広","後草","江ケ崎","江ケ崎１２～２２、１２７～１４０、１７０９、１７２３－３、","溝原","行内","高生","三川","蛇園","秋田","舟戸","松ケ谷","上永井","新町","神宮寺","仁玉","清滝","清和乙","清和甲","西足洗","川口","泉川","倉橋","足川","大間手","大塚原","中谷里","長尾","長部","椎名内","鏑木","東足洗","南堀之内","入野","萩園","八木","塙","飯岡","平松","米込","野中","櫻井","狢野","萬歳","萬力"],"習志野市":["茜浜","屋敷","花咲","香澄","鷺沼","鷺沼台","実籾","実籾本郷","芝園","秋津","新栄","泉町","奏の杜","袖ケ浦","大久保","谷津","谷津町","津田沼","東習志野","藤崎","本大久保"],"柏市":["あかね町","あけぼの","かやの町","しいの木台","つくしが丘","ひばりが丘","みどり台","旭町","伊勢原","永楽台","加賀","花野井","関場町","岩井","岩井新田","亀甲台町","吉野沢","逆井","逆井藤ノ台","金山","呼塚","呼塚新田","戸張","戸張新田","五條谷","光ケ丘","光ケ丘団地","向原町","高田","高南台","高柳","高柳新田","今谷上町","今谷南町","根戸","根戸新田","桜台","篠籠田","若柴","若白毛","若葉町","手賀","手賀の杜","手賀新田","酒井根","十余二","宿連寺","曙橋","小青田","松ケ崎","松ケ崎新田","松葉町","上利根","常盤台","新逆井","新十余二","新柏","新富町","水道橋","正連寺","西原","西山","西町","西柏台","青田新田飛地","青葉台","千間橋","千代田","泉","泉村新田","泉町","染井入新田","船戸","船戸山高野","増尾","増尾台","大井","大井新田","大山台","大室","大青田","大津ケ丘","大塚町","大島田","中央","中央町","中原","中十余二","中新宿","塚崎","東","東逆井","東山","東上町","東台本町","東中新宿","東柏","藤ケ谷","藤ケ谷新田","藤心","南逆井","南高柳","南増尾","南柏","南柏中央","日立台","柏","柏インター東","柏インター南","柏の葉","柏下","柏中村下","柏堀之内新田","八幡町","富里","布施","布施下","布施新町","布施新田","布瀬","布瀬新田","風早","片山","片山新田","弁天下","豊四季","豊四季台","豊住","豊上町","豊町","豊平町","北柏","北柏台","末広町","箕輪","箕輪新田","名戸ケ谷","明原","弥生町","柳戸","緑ケ丘","緑台","鷲野谷","鷲野谷新田"],"勝浦市":["鵜原","花里","蟹田","貝掛","関谷","吉尾","興津","興津久保山台","串浜","荒川","佐野","市野郷","市野川","守谷","宿戸","出水","勝浦","小羽戸","小松野","松部","松野","上植野","上野","植野","植野元宮田","新官","新戸","杉戸","赤羽根","川津","台宿","大森","大森上植野入会地","大沢","大楠","沢倉","中倉","中谷","中島","中里","南山田","白井久保","白木","浜行川","浜勝浦","部原","平田","法花","芳賀","墨名","名木"],"市原市":["うるいど南","ちはら台西","ちはら台東","ちはら台南","旭五所","安久谷","安須","磯ケ谷","引田","永吉","奥野","押沼","荻作","下野","下矢田","加茂","海士有木","海保","皆吉","外部田","柿木台","栢橋","岩","岩崎","岩崎西","岩野見","喜多","菊間","吉沢","久々津","久保","宮原","牛久","玉前","玉前西","金剛地","金沢","駒込","君塚","郡本","迎田","月崎","月出","権現堂","犬成","原田","古市場","古都辺","古敷谷","戸面","五井","五井海岸","五井金杉","五井西","五井中央西","五井中央東","五井中央南","五井東","五井南海岸","五所","光風台","更級","江子田","高坂","高倉","高滝","高田","国分寺台中央","国本","今津朝山","今富","根田","佐是","桜台","山口","山小川","山倉","山田","山田橋","山木","姉崎","姉崎海岸","姉崎西","姉崎東","市原","市場","糸久","寺谷","若宮","十五沢","宿","出津","出津西","潤井戸","勝間","小折","小草畑","小谷田","小田部","松ケ島","松ケ島西","松崎","上原","上高根","新井","新巻","新生","新堀","深城","真ケ谷","神崎","神代","諏訪","水沢","菅野","瀬又","西五所","西広","西国吉","西国分寺台","西野","西野谷","青柳","青柳海岸","青柳北","青葉台","石神","石川","石塚","折津","千種","千種海岸","川在","泉台","浅井小向","惣社","相川","草刈","村上","大厩","大桶","大久保","大戸","大作","大蔵","大坪","大和田","滝口","辰巳台西","辰巳台東","池和田","中","中高根","中野","朝生原","町田","椎の木台","椎津","鶴舞","天羽田","田尾","田淵","田淵旧日竹","土宇","島田","島野","東五所","東国吉","東国分寺台","藤井","徳氏","奈良","南岩崎","南国分寺台","二日市場","廿五里","能満","馬立","柏原","白金町","白塚","畑木","八幡","八幡浦","八幡海岸通","八幡石塚","八幡北町","飯給","飯沼","番場","不入","不入斗","武士","風戸","福増","分目","平蔵","平田","平野","米原","米沢","片又木","奉免","豊成","北国分寺台","堀越","本郷","万田野","妙香","門前","野毛","矢田","柳原","柳川","有秋台西","有秋台東","葉木","養老","立野","櫃挾","藪"],"流山市":["おおたかの森西","おおたかの森東","おおたかの森南","おおたかの森北","こうのす台","下花輪","加","宮園","桐ケ谷","駒木","駒木台","古間木","後平井","向小金","江戸川台西","江戸川台東","三輪野山","市野谷","思井","芝崎","若葉台","十太夫","小屋","松ケ丘","上貝塚","上新宿","上新宿新田","森のロジスティクスパーク","深井新田","西初石","西松ケ丘","西深井","西平井","青田","前ケ崎","前平井","大畔","谷","中","中野久木","長崎","東初石","東深井","南","南流山","美原","美田","鰭ケ崎","富士見台","平方","平方村新田","平和台","北","名都借","木","野々下","流山"],"八千代市":["ゆりのき台","下高野","下市場","萱田","萱田町","吉橋","桑橋","桑納","高津","高津東","佐山","勝田","勝田台","勝田台南","勝田台北","小池","上高野","真木野","神久保","神野","村上","村上南","大学町","大和田","大和田新田","島田","島田台","麦丸","八千代台西","八千代台東","八千代台南","八千代台北","尾崎","平戸","米本","保品","堀の内","緑が丘","緑が丘西"],"我孫子市":["つくし野","栄","岡発戸","岡発戸新田","下ケ戸","下沼田","我孫子","我孫子新田","久寺家","古戸","呼塚新田","湖北台","江蔵地","高野山","高野山新田","根戸","根戸新田","三河屋新田","柴崎","柴崎台","若松","寿","上沼田","新々田","新木","新木村下","新木野","青山","青山台","泉","浅間前新田","船戸","相島新田","台田","大作新田","中沼田","中峠","中峠村下","中峠台","中里","中里新田","天王台","都","都部","都部新田","都部村新田","東我孫子","南新木","南青山","日の出","日秀","日秀新田","白山","布佐","布佐下新田","布佐酉町","布佐平和台","布施","布施下","並木","弁天下","北新田","本町","緑"],"鴨川市":["粟斗","磯村","押切","横渚","横尾","下小原","花房","貝渚","滑谷","釜沼","吉尾西","吉尾平塚","宮","宮山","京田","金束","古畑","広場","江見外堀","江見吉浦","江見西真門","江見青木","江見太夫崎","江見東真門","江見内遠野","佐野","細野","坂東","四方木","寺門","主基西","小湊","松尾寺","上","上小原","成川","清澄","西","西江見","西山","西町","川代","前原","太海","太海西","太海浜","太田学","太尾","打墨","代","大山平塚","大川面","大幡","大里","池田","竹平","仲","仲町","天津","天面","田原西","東","東元浜荻飛地","東江見","東町","奈良林","内浦","南小町","二子","畑","八色","浜荻","平塚","北小町","北風原","来秀","和泉"],"鎌ケ谷市":["くぬぎ山","粟野","右京塚","鎌ケ谷","丸山","串崎新田","軽井沢","佐津間","初富","初富本町","新鎌ケ谷","西佐津間","西道野辺","中央","中佐津間","中沢","中沢新町","東鎌ケ谷","東初富","東中沢","東道野辺","道野辺","道野辺中央","道野辺本町","南鎌ケ谷","南佐津間","南初富","馬込沢","富岡","北初富","北中沢"],"君津市":["かずさ小糸","愛宕","芋窪","浦田","奥米","黄和田畑","荻作","下湯江","加名盛","賀恵渕","外箕輪","釜生","鎌滝","岩出","吉野","久保","久留里","久留里市場","久留里大谷","久留里大和田","宮下","栗坪","君津","君津台","郡","戸崎","向郷","広岡","糠田","糠田飛地","行馬","香木原","高坂","高水","根本","坂田","坂畑","作木","笹","皿引","三直","三田","山高原","山滝野","山本","市宿","糸川","寺沢","鹿野山","宿原","小香","小山野","小市部","小糸大谷","小櫃台","上","上新田","上湯江","常代","植畑","新御堂","人見","杉谷","正木","清和市場","西粟倉","西原","西坂田","西猪原","西日笠","青柳","折木沢","川谷","川俣","泉","草牛","草川原","蔵玉","台","大井","大井戸","大岩","大戸見","大戸見旧名殿","大坂","大山野","大中","大野台","大和田","大鷲","大鷲新田","滝原","中島","中富","中野","長石","長谷川","塚原","辻森","貞元","怒田","怒田沢","東粟倉","東坂田","東猪原","東日笠","藤林","内箕輪","内蓑輪","南久保","南子安","二入","日渡根","馬登","白駒","八重原","八幡","尾車","俵田","浜子","富田","福岡","平山","平田","法木","法木作","豊英","豊田","北久保","北子安","末吉","箕輪","杢師","柳城","陽光台","利根","旅名","練木","六手"],"富津市":["一色","宇藤原","押切","横山","恩田","下飯野","加藤","花香谷","花輪","海良","関","関尻","岩坂","岩瀬","岩本","亀沢","亀田","近藤","金谷","絹","御代原","更和","高溝","佐貫","桜井","桜井総稱鬼泪山","笹毛","山中","山脇","志駒","寺尾","篠部","小久保","小志駒","障子谷","上","上後","上飯野","新井","新富","数馬","西川","西大和田","青木","千種新田","川名","前久保","相川","相野谷","台原","大森","大川崎","大田和","大堀","竹岡","中","長崎","鶴岡","田原","田倉","東大和田","二間塚","売津","萩生","八田沼","八幡","不入斗","富津","宝竜寺","豊岡","望井","本郷","湊","梨沢","六野"],"浦安市":["海楽","港","高洲","今川","千鳥","鉄鋼通り","東野","当代島","日の出","入船","猫実","美浜","富岡","富士見","舞浜","弁天","北栄","堀江","明海"],"四街道市":["さちが丘","さつきケ丘","たかおの杜","つくし座","みそら","みのり町","めいわ","もねの里","旭ケ丘","下志津新田","萱橋","亀崎","吉岡","栗山","山梨","四街道","鹿渡","鹿放ケ丘","小名木","上野","成山","千代田","大日","鷹の台","池花","中央","中台","中野","長岡","内黒田","南波佐間","美しが丘","物井","和田","和良比"],"袖ケ浦市":["のぞみ野","阿部","永吉","永地","横田","下宮田","下根岸","下新田","下泉","岩井","吉野田","久保田","玉野","高谷","今井","坂戸市場","三ツ作","三箇","三黒","勝","上宮田","上泉","神納","川原井","蔵波","蔵波台","袖ケ浦駅前","打越","代宿","大曽根","大竹","大鳥居","滝の口","谷中","中袖","長浦","長浦駅前","椎の森","堂谷","奈良輪","南袖","飯富","百目木","福王台","北袖","野田","野里","林"],"八街市":["みどり台","榎戸","岡田","沖","沖渡","雁丸","希望ケ丘","吉倉","根古谷","砂","山田台","四木","小谷流","上砂","勢田","泉台","大関","大谷流","大木","滝台","中央","朝日","東吉田","八街い","八街に","八街は","八街へ","八街ほ","八街ろ","富山","文違","木原","用草"],"印西市":["つくりや台","みどり台","安食卜杭","浦幡新田","浦部","浦部村新田","押付","下井","下曽根","角田","笠神","鎌苅","岩戸","亀成","吉高","吉田","結縁寺","原","原山","戸神","戸神台","荒野","行徳","高花","高西新田","佐野屋","桜野","山田","師戸","鹿黒","鹿黒南","若萩","酒直卜杭","宗甫","将監","小倉","小倉台","小林","小林浅間","小林大門下","小林北","松崎","松崎台","松虫","松木","甚兵衛","瀬戸","西の原","川向","泉","泉野","浅間前","船尾","相嶋","草深","造谷","多々羅田","大廻","大森","大塚","滝","滝野","竹袋","中","中央南","中央北","中根","中田切","長門屋","東の原","内野","萩原","萩埜","白幡","発作","美瀬","武西","武西学園台","舞姫","物木","平岡","平賀","平賀学園台","別所","牧の原","牧の台","牧の木戸","本埜小林","木下","木下東","木下南","木刈","竜腹寺","和泉","和泉屋"],"白井市":["けやき台","河原子","今井","根","桜台","笹塚","七次台","十余一","神々廻","清戸","清水口","西白井","折立","大山口","大松","谷田","池の上","中","南山","白井","富塚","冨士","武西","復","平塚","堀込","名内","木","野口"],"富里市":["久能","御料","高松","高野","根木名","七栄","十倉","新橋","新中沢","大和","中沢","日吉倉","日吉台","美沢","立沢","立沢新田"],"南房総市":["安馬谷","井野","下滝田","下堀","加茂","海老敷","丸山平塚","丸本郷","岩糸","吉沢","久枝","久保","宮下","宮谷","沓見","検儀谷","犬掛","古川","御子神","御庄","荒川","高崎","合戸","三坂","山下","山田","山名","市部","珠師ケ谷","小浦","小戸","上滝田","上堀","西原","石神","石堂","石堂原","千倉町宇田","千倉町久保","千倉町忽戸","千倉町瀬戸","千倉町千田","千倉町川戸","千倉町川口","千倉町川合","千倉町大貫","千倉町大川","千倉町南朝夷","千倉町白間津","千倉町白子","千倉町平磯","千倉町平舘","千倉町北朝夷","千倉町牧田","千代","川上","川谷","川田","前田","増間","大井","大学口","谷向","池之内","竹内","中","二部","白子","白浜町乙浜","白浜町根本","白浜町滝口","白浜町白浜","富浦町宮本","富浦町居倉","富浦町原岡","富浦町手取","富浦町深名","富浦町青木","富浦町多田良","富浦町大津","富浦町丹生","富浦町南無谷","富浦町福澤","富浦町豊岡","府中","平久里下","平久里中","平塚","峰","本織","明石","和田町下三原","和田町花園","和田町海発","和田町五十蔵","和田町黒岩","和田町柴","和田町小向","和田町小川","和田町松田","和田町沼","和田町上三原","和田町真浦","和田町仁我浦","和田町石堂","和田町中三原","和田町白渚","和田町布野","和田町和田","和田町磑森"],"匝瑳市":["みどり平","安久山","横須賀","荻野","加多古","貝塚","栢田","亀崎","吉崎","吉田","久方","宮本","金原","公崎","高","高野","今泉","山桑","時曽根","若潮町","春海","小高","松山","上谷中","城下","新","新堀","生尾","西小笹","川向","川辺","大浦","大寺","大保里","大堀","中台","長岡","長丘","長谷","椿","田久保","登戸","東小笹","東谷","内山","南山崎","南神崎","入山崎","八日市場イ","八日市場ニ","八日市場ハ","八日市場ホ","八日市場ロ","八辺","飯高","飯倉","飯倉台","飯多香","飯塚","富岡","蕪里","平木","米持","片子","堀川","堀之内","木積","野手"],"香取市":["みずほ台","阿玉川","阿玉台","伊地山","磯山","一ノ分目","羽根川","岡飯田","下小川","下小堀","下小野","下飯田","加藤洲","貝塚","釜塚","苅毛","観音","関","岩ケ崎台","岩部","旗鉾","吉原","久保","境島","玉造","桐谷","九美上","古内","五郷内","公官洲","荒北","香取","高萩","高野","佐原イ","佐原ニ","佐原ハ","佐原ホ","佐原ロ","三ノ分目","三島","山川","山倉","山之辺","市和田","志高","寺内","篠原イ","篠原ロ","助沢","小見","小見川","小川","昭和町","上小川","上小堀","織幡","新々田","新市場","新寺","新部","新里","森戸","神生","仁良","西坂","西田部","西部田","西和田","石納","川上","川尻","川頭","扇島","増田","多田","大角","大戸","大戸新田","大戸川","大根","大崎","大倉","大倉丁子","大島","沢","谷中","竹之内","中洲","虫幡","丁子","長岡","長山","長島","鳥羽","津宮","田部","鴇崎","内野","南原地新田","入会地","白井","八筋川","八日市場","八本","鳩山","飯島","富田","布野","府馬","附洲新田","福田","分郷","米野井","片野","返田","北","北原地新田","牧野","堀之内","本郷","本矢作","木内","木内虫幡上小堀入会地大平","野間谷原","野田","油田","与倉","竜谷","和泉","笄島"],"山武市":["井之内","雨坪","横田","沖渡","下横地","下布田","戸田","五木田","市場","寺崎","実門","柴原","小松","小泉","松ヶ谷","松尾町引越","松尾町猿尾","松尾町下大蔵","松尾町下之郷","松尾町下野","松尾町金尾","松尾町古和","松尾町五反田","松尾町広根","松尾町高富","松尾町山室","松尾町借毛本郷","松尾町祝田","松尾町小川","松尾町松尾","松尾町上大蔵","松尾町水深","松尾町折戸","松尾町大堤","松尾町谷津","松尾町田越","松尾町八田","松尾町富士見台","松尾町武野里","松尾町蕪木","松尾町本水深","松尾町本柏","松尾町木刀","上横地","埴谷","植草","新泉","森","真行寺","親田","成東","川崎","早船","草深","大木","中津田","津辺","椎崎","殿台","島","嶋戸","湯坂","日向台","白幡","板川","板中新田","板附","美杉野","姫島","富口","富田","富田幸谷","武勝","本須賀","麻生新田","木原","木戸","野堀","矢部","蓮沼イ","蓮沼ニ","蓮沼ハ","蓮沼ホ","蓮沼ロ","蓮沼平","和田"],"いすみ市":["引田","荻原","下原","下布施","柿和田","楽町","苅谷","岩船","行川","高谷","国府台","今関","佐室","細尾","作田","札森","山田","釈迦谷","若山","小高","小沢","小池","小又井","松丸","上布施","新田","新田若山深堀入会地","新田野","深谷","深堀","神置","須賀谷","正立寺","増田","大原","大原最上台","大原台","大野","大和田","沢部","長志","島","日在","能実","八乙女","万木","岬町井沢","岬町榎沢","岬町押日","岬町嘉谷","岬町鴨根","岬町岩熊","岬町桑田","岬町江場土","岬町三門","岬町市野々","岬町谷上","岬町中原","岬町中滝","岬町長者","岬町椎木","岬町東小高","岬町東中滝","岬町和泉","弥正"],"大網白里市":["ながた野","みずほ台","みどりが丘","みやこ野","永田","下ヶ傍示","柿餅","萱野","季美の森南","金谷郷","九十根","駒込","桂山","経田","砂田","細草","山口","四天木","小西","小中","上貝塚","上谷新田","神房","星谷","清水","清名幸谷","大竹","大網","池田","長国","東駒込","南横川","南玉","南今泉","南飯塚","二之袋","富田","仏島","北横川","北吉田","北今泉","北飯塚","木崎","餅木","柳橋","養安寺"],"印旛郡酒々井町":["ふじき野","伊篠","伊篠新田","下岩橋","下台","今倉新田","篠山新田","酒々井","上岩橋","上本佐倉","中央台","中川","東酒々井","馬橋","柏木","飯積","尾上","墨","本佐倉"],"印旛郡栄町":["安食","安食台","安食卜杭新田","押付","興津","三和","四ッ谷","四箇","酒直","酒直台","須賀","生板鍋子新田","西","請方","曽根","大森","中谷","長門谷","南","南ケ丘","布鎌酒直","布太","北","北辺田","麻生","矢口","矢口神明","竜角寺台","龍ケ崎町歩","龍角寺","和田","脇川"],"香取郡神崎町":["郡","古原","高谷","今","四季の丘","十三間戸","小松","松崎","植房","新","神崎神宿","神崎本宿","大貫","藤の台","武田","並木","毛成","立野"],"香取郡多古町":["井戸山","一鍬田","間倉","喜多","牛尾","五反田","御所台","高津原","坂","寺作","次浦","十余三","出沼","水戸","西古内","千田","川島","染井","船越","多古","大高","大門","谷三倉","中村新田","島","東輝","東松崎","南玉造","南借当","南中","南並木","南和田","飯笹","桧木","方田","北中","本三倉","林"],"香取郡東庄町":["粟野","羽計","夏目","宮本","宮野台","窪野谷","高部","今郡","笹川い","笹川ろ","舟戸","小貝野","小座","小南","新宿","神田","青馬","石出","大久保","大友","谷津","東今泉","東和田","八重穂","平山"],"山武郡九十九里町":["粟生","下貝塚","荒生","細屋敷","作田","宿","小関","真亀","真亀新田","西野","田中荒生","藤下","不動堂","片貝"],"山武郡芝山町":["下吹入","岩山","宮崎","境","香山新田","高谷","高田","山中","山田","芝山","小原子","小池","上吹入","新井田","新井田新田","大台","大里","朝倉","殿部田","飯櫃","菱田","宝馬","牧野"],"山武郡横芝光町":["姥山","遠山","於幾","横芝","屋形","宮川","牛熊","栗山","原方","古川","坂田","坂田池","市野原","寺方","篠本","篠本根切","芝崎","芝崎南","取立","小川台","小堤","小田部","上原","新井","新島","曽根合","台","谷台","谷中","中台","虫生","長山台","長倉","鳥喰下","鳥喰上","鳥喰新田","二又","尾垂","富下","母子","宝米","傍示戸","北清水","木戸","木戸台","目篠","両国新田"],"長生郡一宮町":["一宮","宮原","綱田","新地","新地甲","新地丙","船頭給","田町","東野","東浪見","白山","本給"],"長生郡睦沢町":["下之郷","河須ケ谷","岩井","佐貫","寺崎","小滝","上市場","上之郷","森","川島","大上","大谷木","長楽寺","北山田","北山田寺崎新田","妙楽寺"],"長生郡長生村":["一松","一松乙","一松甲","一松丁","一松飛地甲","一松丙","一松戊","岩沼","岩沼飛地","宮成","驚","金田","七井土","小泉","信友","水口","曽根","中之郷","入山津","北水口","本郷","薮塚","六ツ野飛地"],"長生郡白子町":["関","牛込","驚","古所","五井","幸治","中里","剃金","南日当","八斗","浜宿","福島","北高根","北日当"],"長生郡長柄町":["榎本","金谷","刑部","高山","国府里","桜谷","皿木","山根","山之郷","小榎本","上野","針ケ谷","千代丸","船木","大津倉","大庭","中野台","長富","長柄山","田代","鴇谷","徳増","味庄","立鳥","力丸","六地蔵"],"長生郡長南町":["下小野田","笠森","関原","岩川","岩撫","給田","今泉","佐坪","坂本","山内","市野々","芝原","小生田","小沢","上小野田","深沢","須田","水沼","千手堂","千田","蔵持","棚毛","地引","竹林","中原","長南","美原台","米満","報恩寺","豊原","本台","又富","茗荷沢"],"夷隅郡大多喜町":["粟又","伊保田","宇筒原","猿稲","押沼","横山","下大多喜","会所","葛藤","久我原","久保","弓木","原内","黒原","紺屋","桜台","三条","三又","市川","紙敷","小沢又","小谷松","小田代","小土呂","小内","小内笛倉入会","小苗","庄司","松尾","上原","上原西部田柳原入会","新丁","森宮","西部田","石神","川畑","泉水","船子","大戸","大多喜","大田代","中野","笛倉","田代","田丁","湯倉","筒森","馬場内","八声","板谷","百鉾","部田","平沢","堀切","堀之内","面白","弥喜用","柳原"],"夷隅郡御宿町":["岩和田","久保","御宿台","高山田","七本","実谷","上布施","新町","須賀","浜","六軒町"],"安房郡鋸南町":["奥山","横根","下佐久間","岩井袋","吉浜","元名","江月","市井原","勝山","小保田","上佐久間","大崩","大六","大帷子","中佐久間","保田","竜島"]}}