{"prefecture":"熊本県","cities":{"熊本市中央区":["安政町","井川淵町","横紺屋町","横手","岡田町","下通","河原町","花畑町","宮内","魚屋町","京町","京町本丁","琴平","琴平本町","九品寺","慶徳堀町","迎町","古桶屋町","古京町","古城町","古川町","古大工町","湖東","呉服町","江津","国府","国府本町","黒髪","紺屋阿弥陀寺町","紺屋今町","紺屋町","細工町","桜町","三郎","山崎町","子飼本町","室園町","手取本町","十禅寺","出水","春竹町","小沢町","松原町","上京塚町","上水前寺","上鍛冶屋町","上通町","上林町","城東町","新屋敷","新市街","新大江","新鍛冶屋町","新町","神水","神水本町","辛島町","水前寺","水前寺公園","水道町","菅原町","世安","世安町","西阿弥陀寺町","西子飼町","西唐人町","千葉城町","川端町","船場町","船場町下","草葉町","帯山","大江","大江本町","鍛冶屋町","段山本町","中央街","中唐人町","通町","坪井","渡鹿","島崎","東阿弥陀寺町","東京塚町","東子飼町","内坪井町","南熊本","南千反畑町","南坪井町","二の丸","萩原町","白山","八王寺町","板屋町","平成","米屋町","保田窪","北千反畑町","本丸","本山","本山町","本荘","本荘町","万町","妙体寺町","弥生町","薬園町","練兵町","壺川"],"熊本市東区":["栄町","榎町","下江津","下南部","花立","画図町下江津","画図町下無田","画図町重富","画図町所島","画図町上無田","画図東","吉原町","弓削町","京塚本町","錦ケ丘","月出","健軍","健軍本町","戸島","戸島西","戸島町","戸島本町","湖東","御領","広木町","江津","佐土原","桜木","三郎","山ノ神","山ノ内","鹿帰瀬町","若葉","秋津","秋津新町","秋津町秋田","出水","小山","小山町","小峯","昭和町","沼山津","上南部","上南部町","新外","新生","新南部","神園","神水本町","水源","西原","石原","石原町","帯山","中江町","長嶺西","長嶺東","長嶺南","渡鹿","東京塚町","東町","東本町","東野","南町","八反田","尾ノ上","平山町","保田窪","保田窪本町"],"熊本市西区":["横手","沖新町","河内町河内","河内町岳","河内町船津","河内町大多尾","河内町東門寺","河内町白浜","河内町面木","河内町野出","花園","京町本丁","戸坂町","高橋町","出町","春日","小島","小島下町","小島上町","松尾","松尾町近津","松尾町平山","上熊本","上高橋","上松尾町","上代","城山下代","城山上代町","城山大塘","城山半田","城山薬師","新港","新土河原","西松尾町","谷尾崎町","池亀町","池上町","池田","中原町","中松尾町","中島町","津浦町","田崎","田崎町","田崎本町","島崎","二本木","八島","八島町","稗田町","野中","蓮台寺"],"熊本市南区":["奥古閑町","会富町","海路口町","刈草","近見","元三町","御幸西","御幸西無田町","御幸笛田","御幸笛田町","御幸木部","御幸木部町","護藤町","幸田","江越","荒尾","荒尾町","合志","今町","砂原町","十禅寺","出仲間","上ノ郷","城南町さんさん","城南町阿高","城南町永","城南町下宮地","城南町宮地","城南町隈庄","城南町高","城南町今吉野","城南町坂野","城南町出水","城南町赤見","城南町千町","城南町丹生宮","城南町築地","城南町沈目","城南町陳内","城南町塚原","城南町碇","城南町島田","城南町東阿高","城南町藤山","城南町舞原","城南町六田","城南町鰐瀬","川口町","川尻","銭塘町","孫代町","中無田町","田井島","田迎","田迎町田井島","田迎町良町","土河原町","島町","鳶町","内田町","南高江","日吉","馬渡","白石町","白藤","薄場","薄場町","畠口町","八王寺町","八幡","八分字町","美登里町","浜口町","富合町榎津","富合町廻江","富合町古閑","富合町菰江","富合町御船手","富合町国町","富合町志々水","富合町釈迦堂","富合町小岩瀬","富合町上杉","富合町新","富合町杉島","富合町清藤","富合町西田尻","富合町大町","富合町田尻","富合町南田尻","富合町平原","富合町木原","富合町硴江","富合町莎崎","平成","平田","並建町","無田口町","野口","野口町","野田","流通団地","良町"],"熊本市北区":["下硯川","下硯川町","改寄町","梶尾町","釜尾町","弓削","硯川町","貢町","高平","黒髪","黒髪町坪井","山室","四方寄町","鹿子木町","室園町","小糸山町","植木町鞍掛","植木町伊知坊","植木町一木","植木町円台寺","植木町荻迫","植木町岩野","植木町亀甲","植木町宮原","植木町古閑","植木町後古閑","植木町広住","植木町轟","植木町今藤","植木町山本","植木町舟島","植木町小野","植木町上古閑","植木町植木","植木町色出","植木町正清","植木町清水","植木町石川","植木町大井","植木町大和","植木町滴水","植木町田底","植木町投刀塚","植木町鐙田","植木町那知","植木町内","植木町富応","植木町舞尾","植木町平井","植木町平原","植木町平野","植木町米塚","植木町辺田野","植木町豊岡","植木町豊田","植木町味取","植木町木留","植木町有泉","植木町鈴麦","清水岩倉","清水亀井町","清水新地","清水町室園","清水町松崎","清水町打越","清水東町","清水本町","清水万石","西梶尾町","太郎迫町","打越町","大窪","大鳥居町","池田","津浦町","鶴羽田","鶴羽田町","兎谷","徳王","徳王町","楠","楠野町","八景水谷","飛田","武蔵ケ丘","北迫町","麻生田","万楽寺町","明徳町","立福寺町","龍田","龍田弓削","龍田陳内","和泉町","楡木"],"八代市":["旭中央通","井上町","井揚町","永碇町","塩屋町","横手新町","横手町","横手本町","黄金町","岡町小路","岡町谷川","岡町中","沖町","花園町","海士江町","宮地町","興国町","興善寺町","鏡町塩浜","鏡町下村","鏡町下有佐","鏡町貝洲","鏡町鏡","鏡町鏡村","鏡町芝口","鏡町上鏡","鏡町中島","鏡町内田","鏡町宝出","鏡町北新地","鏡町野崎","鏡町有佐","鏡町両出","錦町","郡築一番町","郡築九番町","郡築五番町","郡築三番町","郡築四番町","郡築七番町","郡築十一番町","郡築十二番町","郡築十番町","郡築二番町","郡築八番町","郡築六番町","迎町","建馬町","古閑下町","古閑上町","古閑中町","古閑浜町","古城町","古麓町","港町","高下西町","高下東町","高小原町","高植本町","高島町","催合町","坂本町鮎帰","坂本町鎌瀬","坂本町荒瀬","坂本町坂本","坂本町市ノ俣","坂本町深水","坂本町西部","坂本町川嶽","坂本町中谷","坂本町中津道","坂本町鶴喰","坂本町田上","坂本町百済来下","坂本町百済来上","坂本町葉木","三楽町","三江湖町","蛇籠町","若草町","十条町","出町","昭和同仁町","昭和日進町","昭和明徴町","松江城町","松江町","松江本町","松崎町","上日置町","上片町","上野町","植柳下町","植柳元町","植柳上町","植柳新町","新開町","新港町","新地町","新町","新浜町","水島町","清水町","西宮町","西松江城町","西片町","千丁町吉王丸","千丁町古閑出","千丁町新牟田","千丁町太牟田","千反町","川田町西","川田町東","栴檀町","泉町下岳","泉町柿迫","泉町久連子","泉町栗木","泉町仁田尾","泉町椎原","泉町葉木","泉町樅木","鼠蔵町","袋町","大手町","大村町","大島町","大福寺町","鷹辻町","築添町","竹原町","中片町","中北町","長田町","通町","田中西町","田中町","田中東町","田中北町","渡町","島田町","東町","東片町","東陽町河俣","東陽町小浦","東陽町南","東陽町北","奈良木町","南平和町","二見下大野町","二見洲口町","二見赤松町","二見本町","二見野田崎町","日置町","日奈久栄町","日奈久塩南町","日奈久塩北町","日奈久下西町","日奈久山下町","日奈久上西町","日奈久新開町","日奈久新田町","日奈久大坪町","日奈久竹之内町","日奈久中西町","日奈久中町","日奈久東町","日奈久馬越町","日奈久浜町","日奈久平成町","萩原町","麦島西町","麦島東町","八幡町","毘舎丸町","敷川内町","福正元町","福正町","平山新町","豊原下町","豊原上町","豊原中町","北の丸町","北原町","北平和町","本町","本野町","末広町","妙見町","弥生町","夕葉町","揚町","緑町","葭牟田町"],"人吉市":["井ノ口町","温泉町","下永野町","下原田町","下戸越町","下薩摩瀬町","下漆田町","下城本町","下新町","下青井町","下田代町","下林町","灰久保町","蟹作町","瓦屋町","願成寺町","鬼木町","九日町","駒井田町","原城町","古仏頂町","五日町","合ノ原町","紺屋町","寺町","鹿目町","七地町","七日町","上永野町","上原町","上原田町","上戸越町","上薩摩瀬町","上漆田町","上新町","上青井町","上田代町","上林町","城本町","新町","西間下町","西間上町","西大塚町","赤池原町","赤池水無町","相良町","大工町","大畑町","大畑麓町","大野町","鍛冶屋町","中神町","中青井町","中林町","鶴田町","田町","田野町","土手町","東間下町","東間上町","東漆田町","東大塚町","南願成寺町","南泉田町","南町","二日町","富ケ尾町","宝来町","北願成寺町","北泉田町","蓑野町","木地屋町","矢岳町","矢黒町","浪床町","老神町","麓町"],"荒尾市":["一部","下井手","海陽町","樺","宮内","宮内出目","牛水","金山","原万田","菰屋","荒尾","高浜","桜山町","四ツ山町","住吉町","昭和町","上井手","上平山","水野","西原町","川登","増永","蔵満","大正町","大島","大島町","大平町","東屋形","日の出町","八幡台","府本","平山","本井手","万田","野原","緑ケ丘"],"水俣市":["ひばりケ丘","わらび野","旭町","浦上町","栄町","越小場","塩浜町","葛渡","丸島町","祇園町","久木野","月浦","古賀町","古城","古里","幸町","江添","江南町","港町","桜ケ丘","桜井町","山手町","市渡瀬","汐見町","初野","小津奈木","昭和町","深川","陣内","石坂川","洗切町","多々良町","袋","大園町","大黒町","大川","大迫","築地","中鶴","長崎","長野","長野町","天神町","湯出","南福寺","梅戸町","白浜町","薄原","八ノ窪町","八幡町","百間町","浜","浜松町","浜町","平町","宝川内","牧ノ内","明神町","野口町","緑ケ丘"],"玉名市":["安楽寺","伊倉南方","伊倉北方","永徳寺","横田","横島町横島","横島町共栄","横島町大園","下","下小田","河崎","滑石","岩崎","亀甲","宮原","玉名","月田","向津留","溝上","高瀬","三ツ川","山田","山部田","寺田","秋丸","小島","小浜","小野尻","松木","上小田","青木","青野","石貫","千田川原","川島","川部田","岱明町下沖洲","岱明町下前原","岱明町開田","岱明町古閑","岱明町高道","岱明町三崎","岱明町山下","岱明町庄山","岱明町上","岱明町西照寺","岱明町扇崎","岱明町大野下","岱明町中土","岱明町鍋","岱明町浜田","岱明町野口","大倉","大浜町","築地","中","中坂門田","中尾","津留","天水町小天","天水町竹崎","天水町尾田","天水町部田見","天水町野部田","天水町立花","田崎","南坂門田","箱谷","繁根木","富尾","片諏訪","北坂門田","北牟田","立願寺","両迫間","六田"],"山鹿市":["下吉田","蒲生","菊鹿町阿佐古","菊鹿町下永野","菊鹿町下内田","菊鹿町宮原","菊鹿町五郎丸","菊鹿町山内","菊鹿町松尾","菊鹿町上永野","菊鹿町上内田","菊鹿町相良","菊鹿町太田","菊鹿町池永","菊鹿町長","菊鹿町米原","菊鹿町木野","菊鹿町矢谷","久原","熊入町","古閑","坂田","山鹿","志々岐","寺島","鹿央町岩原","鹿央町広","鹿央町合里","鹿央町持松","鹿央町仁王堂","鹿央町千田","鹿央町霜野","鹿央町大浦","鹿央町中浦","鹿央町梅木谷","鹿央町北谷","鹿校通","鹿北町芋生","鹿北町岩野","鹿北町四丁","鹿北町多久","鹿北町椎持","鹿本町下高橋","鹿本町下分田","鹿本町梶屋","鹿本町御宇田","鹿本町高橋","鹿本町小嶋","鹿本町小柳","鹿本町庄","鹿本町石渕","鹿本町中川","鹿本町中富","鹿本町中分田","鹿本町津袋","鹿本町分田","鹿本町来民","宗方","宗方通","小群","小原","小坂","昭和町","上吉田","城","新町","杉","西牧","石","川端町","泉町","大橋通","中","中央通","長坂","津留","椿井","藤井","鍋田","南島","平山","保多田","方保田","麻生野","名塚"],"菊池市":["旭志伊坂","旭志伊萩","旭志小原","旭志新明","旭志川辺","旭志尾足","旭志弁利","旭志麓","下河原","玉祥寺","隈府","袈裟尾","原","広瀬","今","四町分","市野瀬","七城町岡田","七城町加恵","七城町亀尾","七城町橋田","七城町菰入","七城町甲佐町","七城町荒牧","七城町高田","七城町高島","七城町砂田","七城町山崎","七城町小野崎","七城町新古閑","七城町水次","七城町瀬戸口","七城町清水","七城町蘇崎","七城町台","七城町辺田","七城町流川","七城町林原","重味","出田","小木","森北","深川","西寺","西迫間","赤星","雪野","村田","大平","大琳寺","長田","藤田","班蛇口","稗方","片角","豊間","北宮","木柑子","木庭","木野","野間口","龍門","亘","泗水町永","泗水町亀尾","泗水町吉富","泗水町住吉","泗水町田島","泗水町南田島","泗水町富納","泗水町福本","泗水町豊水"],"宇土市":["旭町","伊無田町","一里木町","浦田町","栄町","下網田町","花園台町","花園町","岩古曽町","宮庄町","境目町","栗崎町","恵塚町","古城町","古保里町","戸口町","高柳町","笹原町","三拾町","住吉町","松原町","松山町","上網田町","城塚町","城之浦町","新開町","新小路町","新松原町","新町","神合町","神馬町","水町","石橋町","石小路町","赤瀬町","船場町","善道寺町","走潟町","築籠町","長浜町","椿原町","定府町","南段原町","入地町","馬之瀬町","北段原町","本町","網引町","網津町","門内町","野鶴町","立岡町"],"上天草市":["松島町阿村","松島町教良木","松島町合津","松島町今泉","松島町内野河内","大矢野町維和","大矢野町上","大矢野町中","大矢野町登立","大矢野町湯島","姫戸町二間戸","姫戸町姫浦","龍ケ岳町高戸","龍ケ岳町大道","龍ケ岳町樋島"],"宇城市":["三角町郡浦","三角町戸馳","三角町三角浦","三角町手場","三角町前越","三角町大口","三角町大田尾","三角町中村","三角町波多","三角町里浦","小川町河江","小川町江頭","小川町住吉","小川町小川","小川町新田","小川町新田出","小川町西海東","小川町西北小川","小川町川尻","小川町中小野","小川町東海東","小川町東小川","小川町南海東","小川町南小川","小川町南小野","小川町南新田","小川町南部田","小川町不知火","小川町北海東","小川町北小野","小川町北新田","小川町北部田","松橋町きらら","松橋町浦川内","松橋町久具","松橋町曲野","松橋町古保山","松橋町御船","松橋町砂川","松橋町松橋","松橋町松山","松橋町西下郷","松橋町浅川","松橋町大野","松橋町竹崎","松橋町東松崎","松橋町内田","松橋町南豊崎","松橋町萩尾","松橋町豊崎","松橋町豊福","松橋町両仲間","不知火町浦上","不知火町永尾","不知火町亀松","不知火町御領","不知火町高良","不知火町小曽部","不知火町松合","不知火町大見","不知火町長崎","不知火町柏原","豊野町安見","豊野町下郷","豊野町山崎","豊野町糸石","豊野町上郷","豊野町巣林","豊野町中間"],"阿蘇市":["一の宮町荻の草","一の宮町宮地","一の宮町坂梨","一の宮町三野","一の宮町手野","一の宮町中坂梨","一の宮町中通","一の宮町北坂梨","永草","乙姫","黒川","黒流町","今町","三久保","山田","車帰","狩尾","小倉","小池","小野田","小里","西小園","西町","西湯浦","赤水","跡ケ瀬","蔵原","竹原","的石","湯浦","内牧","南宮原","波野小園","波野小地野","波野新波野","波野赤仁田","波野滝水","波野中江","波野波野","無田","役犬原"],"天草市":["１９７０、１９７４、１９７６、１９８３、１９８８－３、１９９０－５、","２００３、２０５１","旭町","栄町","下浦町","河浦町河浦","河浦町久留","河浦町宮野河内","河浦町今田","河浦町今富","河浦町今富１９３３、１９３９、１９４５、１９５５－４、１９６０、","河浦町崎津","河浦町新合","河浦町白木河内","河浦町立原","河浦町路木","丸尾町","亀場町亀川","亀場町食場","久玉町","宮地岳町","牛深町","魚貫町","古川町","五和町鬼池","五和町御領","五和町手野","五和町城河原","五和町二江","御所浦町横浦","御所浦町御所浦","御所浦町牧島","港町","今釜新町","今釜町","佐伊津町","山の手町","志柿町","小松原町","城下町","浄南町","新和町小宮地","新和町大宮地","新和町大多尾","新和町中田","新和町碇石","深海町","諏訪町","瀬戸町","栖本町河内","栖本町古江","栖本町打田","栖本町湯船原","栖本町馬場","川原新町","川原町","船之尾町","倉岳町浦","倉岳町宮田","倉岳町棚底","太田町","大浜町","中央新町","中村町","天草町下田南","天草町下田北","天草町高浜南","天草町高浜北","天草町大江","天草町大江軍浦","天草町大江向","天草町福連木","東町","東浜町","南新町","南町","楠浦町","二浦町亀浦","二浦町早浦","八幡町","浜崎町","北原町","北浜町","本町下河内","本町新休","本町本","本渡町広瀬","本渡町本戸馬場","本渡町本泉","本渡町本渡","有明町下津浦","有明町小島子","有明町上津浦","有明町須子","有明町赤崎","有明町大浦","有明町大島子","有明町楠甫","枦宇土町"],"合志市":["栄","幾久富","御代志","合生","上庄","上生","須屋","竹迫","福原","豊岡","野々島"],"下益城郡美里町":["安部","永富","遠野","萱野","岩下","岩野","境","栗崎","堅志田","原町","原田","古閑","甲佐平","今","佐俣","坂貫","坂本","三加","三和","小市野","小筵","松野原","畝野","清水","石野","川越","早楠","大井早","大窪","大沢水","中","中郡","中小路","長尾野","津留","椿","土喰","洞岳","二和田","馬場","柏川","白石野","払川","豊富","名越谷","木早川内","涌井"],"玉名郡玉東町":["稲佐","浦田","原倉","山口","上白木","上木葉","西安寺","二俣","白木","木葉"],"玉名郡南関町":["下坂下","関下","関外目","関村","関町","関東","久重","宮尾","高久野","今","細永","四ツ原","小原","上坂下","上長田","相谷","長山","肥猪","肥猪町","豊永"],"玉名郡長洲町":["永塩","宮野","高浜","上沖洲","清源寺","折崎","長洲","梅田","姫ケ浦","腹赤","名石浜","有明"],"玉名郡和水町":["榎原","下津原","岩","岩尻","久井原","久米野","原口","江栗","江田","高野","山十町","志口永","焼米","上十町","上板楠","上和仁","瀬川","西吉地","前原","大屋","大田黒","中十町","中林","中和仁","長小田","津田","東吉地","藤田","内田","日平","萩原","板楠","平野","米渡尾","野田","用木","和仁","竈門","蜻浦"],"菊池郡大津町":["引水","下町","灰塚","外牧","岩坂","錦野","古城","高尾野","室","新","森","真木","陣内","吹田","杉水","瀬田","大津","大林","中島","町","美咲野","平川","矢護川"],"菊池郡菊陽町":["沖野","花立","久保田","曲手","原水","戸次","光の森","向陽台","新山","辛川","杉並台","津久礼","馬場楠","武蔵ヶ丘","武蔵ヶ丘北"],"阿蘇郡南小国町":["赤馬場","中原","満願寺"],"阿蘇郡小国町":["下城","宮原","黒渕","上田","西里","北里"],"阿蘇郡産山村":["山鹿","産山","大利","田尻","片俣"],"阿蘇郡高森町":["永野原","下切","河原","芹口","高森","上色見","色見","菅山","草部","中","津留","尾下","野尻","矢津田"],"阿蘇郡西原村":["河原","宮山","小森","鳥子","布田"],"阿蘇郡南阿蘇村":["一関","下野","河陰","河陽","吉田","久石","中松","長野","白川","立野","両併"],"上益城郡御船町":["御船","高木","七滝","小坂","上野","陣","水越","滝川","滝尾","田代","辺田見","豊秋","木倉"],"上益城郡嘉島町":["井寺","下仲間","下六嘉","犬渕","上仲間","上島","上六嘉","北甘木","鯰"],"上益城郡益城町":["安永","下陳","宮園","古閑","広崎","寺中","寺迫","小谷","小池","上陳","杉堂","赤井","惣領","辻の城","田原","砥川","島田","馬水","福原","福富","平田","木山"],"上益城郡甲佐町":["安平","横田","下横田","岩下","吉田","坂谷","糸田","芝原","小鹿","上早川","上揚","仁田子","世持","西寒野","西原","船津","早川","大町","中横田","中山","津志田","田口","東寒野","南三箇","白旗","府領","豊内","麻生原","有安","緑町"],"上益城郡山都町":["芦屋田","安方","伊勢","井無田","猿渡","塩原","塩出迫","下山","下市","下川井野","下馬尾","下名連石","仮屋","花上","葛原","鎌野","貫原","橘","郷野原","玉目","金内","犬飼","原","御所","荒谷","高月","高辻","高畑","黒川","今","三ケ","山田","市原","市野原","小笹","小中竹","小峰","上差尾","上寺","上川井野","城原","城平","新小","神ノ前","須原","杉木","菅","菅尾","勢井","成君","千滝","川口","川野","大見口","大平","大野","滝上","男成","長原","長崎","長谷","長田","津留","鶴ケ田","田吉","田所","田小野","島木","東竹原","藤木","南田","二瀬本","二津留","入佐","馬見原","柏","白小野","白石","白藤","畑","八木","尾野尻","浜町","仏原","米生","米迫","方ケ野","北中島","牧野","麻山","万坂","木原谷","目丸","野尻","柳","柳井原","柚木","緑川"],"八代郡氷川町":["河原","吉本","宮原","宮原栄久","高塚","今","鹿島","鹿野","若洲","新田","早尾","大野","中島","島地","網道","野津","有佐","立神","栫"],"葦北郡芦北町":["芦北","井牟田","塩浸","横居木","乙千屋","花岡","海浦","海路","丸山","吉尾","宮浦","宮崎","桑原","計石","古石","高岡","告","国見","黒岩","佐敷","市野瀬","女島","小田浦","松生","上原","大岩","大川内","大尼田","大野","鶴木山","天月","田浦","田浦町","田川","湯浦","道川内","波多島","白岩","白石","白木","八幡","伏木氏","米田","豊岡","立川","箙瀬"],"葦北郡津奈木町":["岩城","小津奈木","千代","津奈木","福浜"],"球磨郡錦町":["一武","西","木上"],"球磨郡多良木町":["奥野","久米","黒肥地","多良木","槻木"],"球磨郡湯前町":["下城","下染田","下村","下里","古城","上染田","上村","上猪","上里","植木","瀬戸口","浅ケ野","中猪","中里","田上","馬場","浜川","野中田"],"球磨郡水上村":["岩野","江代","湯山"],"球磨郡相良村":["四浦","深水","川辺","柳瀬"],"球磨郡五木村":["乙","甲","丙"],"球磨郡山江村":["山田","万江"],"球磨郡球磨村":["一勝地","三ケ浦","神瀬","大瀬","渡"],"球磨郡あさぎり町":["岡原南","岡原北","皆越","上西","上東","上南","上北","深田西","深田東","深田南","深田北","須恵","免田西","免田東"],"天草郡苓北町":["坂瀬川","志岐","上津深江","都呂々","内田","年柄","白木尾","富岡"]}}